{
  "active": false,
  "connections": {
    "When clicking ‘Execute workflow’": {
      "main": [
        [
          {
            "node": "Select rows from a table",
            "type": "main",
            "index": 0
          }
        ]
      ]
    },
    "HTTP Request": {
      "main": [
        [
          {
            "node": "Code",
            "type": "main",
            "index": 0
          }
        ]
      ]
    },
    "Select rows from a table": {
      "main": [
        [
          {
            "node": "HTTP Request",
            "type": "main",
            "index": 0
          }
        ]
      ]
    },
    "Code": {
      "main": [
        [
          {
            "node": "Code1",
            "type": "main",
            "index": 0
          }
        ]
      ]
    },
    "Code1": {
      "main": [
        [
          {
            "node": "Execute a SQL query",
            "type": "main",
            "index": 0
          }
        ]
      ]
    }
  },
  "createdAt": "2025-07-28T12:49:58.224Z",
  "id": "njythNTM1vo55MqQ",
  "isArchived": false,
  "meta": null,
  "name": "Sincronizar Pipelines Moldex",
  "nodes": [
    {
      "parameters": {},
      "type": "n8n-nodes-base.manualTrigger",
      "typeVersion": 1,
      "position": [
        0,
        0
      ],
      "id": "ba9f37d9-8d84-436f-9438-00dc980630a8",
      "name": "When clicking ‘Execute workflow’"
    },
    {
      "parameters": {
        "url": "=https://backend.leadconnectorhq.com/opportunities/pipelines/?locationId={{ $('Webhook').item.json.body.id_location }}",
        "sendHeaders": true,
        "headerParameters": {
          "parameters": [
            {
              "name": "Version",
              "value": "2021-07-28"
            },
            {
              "name": "Authorization",
              "value": "={{ $json.token }}"
            }
          ]
        },
        "options": {}
      },
      "type": "n8n-nodes-base.httpRequest",
      "typeVersion": 4.2,
      "position": [
        400,
        0
      ],
      "id": "b2364814-089b-4a3b-9b7a-51acf286e674",
      "name": "HTTP Request"
    },
    {
      "parameters": {
        "operation": "select",
        "schema": {
          "__rl": true,
          "mode": "list",
          "value": "public"
        },
        "table": {
          "__rl": true,
          "value": "system_ropofy_locations",
          "mode": "list",
          "cachedResultName": "system_ropofy_locations"
        },
        "limit": 1,
        "where": {
          "values": [
            {
              "column": "location_id",
              "value": "={{ $json.body.id_location }}"
            }
          ]
        },
        "options": {}
      },
      "type": "n8n-nodes-base.postgres",
      "typeVersion": 2.6,
      "position": [
        180,
        0
      ],
      "id": "3de5dbd8-cca8-414b-b737-78a5ef6452a3",
      "name": "Select rows from a table",
      "credentials": {
        "postgres": {
          "id": "tfjc18K49daMASdp",
          "name": "Base de datos APIS"
        }
      }
    },
    {
      "parameters": {
        "jsCode": "return $input.first().json.pipelines;"
      },
      "type": "n8n-nodes-base.code",
      "typeVersion": 2,
      "position": [
        620,
        0
      ],
      "id": "5df11390-1403-4346-9f6f-b23995c07225",
      "name": "Code"
    },
    {
      "parameters": {
        "operation": "executeQuery",
        "query": "{{ $json.text }}",
        "options": {
          "queryBatching": "independently",
          "queryReplacement": "={{ $json.values }}"
        }
      },
      "type": "n8n-nodes-base.postgres",
      "typeVersion": 2.6,
      "position": [
        1060,
        0
      ],
      "id": "e436febe-c28a-48a4-a28e-262114598c4f",
      "name": "Execute a SQL query",
      "credentials": {
        "postgres": {
          "id": "ttqvVbC78buoDb38",
          "name": "Moldex DB bi"
        }
      }
    },
    {
      "parameters": {
        "mode": "runOnceForEachItem",
        "jsCode": "const d = $json;\n\nconst query = {\n  text: `\n    INSERT INTO public.\"pipelines\" (\n      \"id\", \"name\", \"stages\", \"showInFunnel\", \"showInPieChart\", \"locationId\", \"created_at\", \"updated_at\"\n    ) VALUES (\n      $1, $2, $3::jsonb, $4, $5, $6, NOW(), NOW()\n    )\n    ON CONFLICT (\"id\") DO UPDATE SET\n      \"name\" = EXCLUDED.\"name\",\n      \"stages\" = EXCLUDED.\"stages\",\n      \"showInFunnel\" = EXCLUDED.\"showInFunnel\",\n      \"showInPieChart\" = EXCLUDED.\"showInPieChart\",\n      \"locationId\" = EXCLUDED.\"locationId\",\n      \"updated_at\" = NOW()\n  `,\n  values: [\n    d.id,\n    d.name,\n    JSON.stringify(d.stages || []),  // stages como JSONB\n    d.showInFunnel || false,\n    d.showInPieChart || false,\n    d.locationId\n  ]\n};\n\nreturn {\n  text: query.text,\n  values: query.values\n};\n"
      },
      "type": "n8n-nodes-base.code",
      "typeVersion": 2,
      "position": [
        840,
        0
      ],
      "id": "61e472b7-a132-4024-b8ff-e7ba1086d9e3",
      "name": "Code1"
    }
  ],
  "pinData": {},
  "repo_name": "ropoflow_workflows_backup",
  "repo_owner": "sebastianOrtizRopofy",
  "repo_path": "ropoflow_workflows_backup",
  "settings": {
    "executionOrder": "v1"
  },
  "staticData": null,
  "tags": [],
  "triggerCount": 0,
  "updatedAt": "2025-07-28T12:50:06.824Z",
  "versionId": "cdb2b94f-c28a-40b2-971b-a42a8f59c269"
}